audiobook_tags/__about__.py
audiobook_tags/__init__.py
audiobook_tags/main.py
audiobook_tags/tags.py
audiobook_tags-1.3.3.dist-info/METADATA
audiobook_tags-1.3.3.dist-info/WHEEL
audiobook_tags-1.3.3.dist-info/entry_points.txt
audiobook_tags-1.3.3.dist-info/licenses/LICENSE.txt
audiobook_tags-1.3.3.dist-info/RECORD
