Metadata-Version: 2.4
Name: audiobook-tags
Version: 1.3.3
Summary: Fix mp3 tags to use in iTunes/iPhone audiobooks.
Project-URL: Homepage, https://andgineer.github.io/audiobook-tags/
Project-URL: Documentation, https://andgineer.github.io/audiobook-tags/
Author-email: Andrey Sorokin <andrey@sorokin.engineer>
License: Copyright (c) 2024 Andrey Sorokin <andrey@sorokin.engineer>
License-File: LICENSE.txt
Keywords: audiobook,iphone,itunes,mp3,tags
Classifier: License :: OSI Approved :: MIT License
Classifier: Operating System :: OS Independent
Classifier: Programming Language :: Python :: 3
Requires-Python: >=3.8
Requires-Dist: eyed3
